LICENSE
README.md
setup.py
fear_module/__init__.py
fear_module/fear.py
fear_module.egg-info/PKG-INFO
fear_module.egg-info/SOURCES.txt
fear_module.egg-info/dependency_links.txt
fear_module.egg-info/requires.txt
fear_module.egg-info/top_level.txt