Metadata-Version: 2.1
Name: fear-module
Version: 1.1
Summary: Python module for making fear apps Fear Application
Home-page: https://github.com/Keker-dev/fear_module
Download-URL: https://github.com/Keker-dev/fear_module/archive/main.zip
Author: Keker
Author-email: timaiv112008@gmail.com
License: MIT License, see LICENSE file
Classifier: License :: OSI Approved :: MIT License
Classifier: Operating System :: OS Independent
Classifier: Intended Audience :: End Users/Desktop
Classifier: Intended Audience :: Developers
Classifier: Programming Language :: Python
Classifier: Programming Language :: Python :: 3
Classifier: Programming Language :: Python :: 3.8
Classifier: Programming Language :: Python :: 3.9
Classifier: Programming Language :: Python :: 3.10
Classifier: Programming Language :: Python :: 3.11
Classifier: Programming Language :: Python :: 3.12
Classifier: Programming Language :: Python :: Implementation :: PyPy
Classifier: Programming Language :: Python :: Implementation :: CPython
License-File: LICENSE
Requires-Dist: comtypes
Requires-Dist: keyboard
Requires-Dist: pillow
Requires-Dist: psutil
Requires-Dist: pycaw
Requires-Dist: pygame
Requires-Dist: pyperclip
